{
	"folder": "hqIrVWSUxA1FCXwI",
	"name": "Rot Guardian",
	"type": "npc",
	"prototypeToken": {
		"flags": {
			"splatter": {
				"bloodColor": ""
			},
			"wall-height": {
				"tokenHeight": 0
			},
			"LocknKey": {
				"LPFormulaFlag": "",
				"LPFormulaOverrideFlag": false,
				"LBFormulaFlag": "",
				"LBFormulaOverrideFlag": false,
				"PickPocketFormulaFlag": "",
				"PickPocketFormulaOverrideFlag": false,
				"LootFormulaFlag": "",
				"PickPocketDCFlag": null,
				"MATTTriggerTileFlag": "",
				"MATTTriggerConditionsFlag": {
					"LockuseKey": "never",
					"LockusePasskey": "never",
					"LockusePick": "never",
					"LockuseBreak": "never",
					"LockuseFree": "never",
					"UsePickPocket": "never"
				}
			},
			"pf2e": {
				"linkToActorSize": true,
				"autoscale": true
			}
		},
		"height": 2,
		"width": 2,
		"name": "Rot Guardian",
		"displayName": 20,
		"actorLink": false,
		"texture": {
			"src": "systems/pf2e/icons/default-icons/npc.svg",
			"anchorX": 0.5,
			"anchorY": 0.5,
			"offsetX": 0,
			"offsetY": 0,
			"fit": "contain",
			"scaleX": 1,
			"scaleY": 1,
			"rotation": 0,
			"tint": "#ffffff",
			"alphaThreshold": 0.75
		},
		"lockRotation": true,
		"rotation": 0,
		"alpha": 1,
		"disposition": -1,
		"displayBars": 20,
		"bar1": {
			"attribute": "attributes.hp"
		},
		"bar2": {
			"attribute": null
		},
		"light": {
			"negative": false,
			"priority": 0,
			"alpha": 0.5,
			"angle": 360,
			"bright": 0,
			"color": null,
			"coloration": 1,
			"dim": 0,
			"attenuation": 0.5,
			"luminosity": 0.5,
			"saturation": 0,
			"contrast": 0,
			"shadows": 0,
			"animation": {
				"type": null,
				"speed": 5,
				"intensity": 5,
				"reverse": false
			},
			"darkness": {
				"min": 0,
				"max": 1
			}
		},
		"sight": {
			"enabled": false,
			"range": 0,
			"angle": 360,
			"visionMode": "basic",
			"color": null,
			"attenuation": 0.1,
			"brightness": 0,
			"saturation": 0,
			"contrast": 0
		},
		"detectionModes": [],
		"occludable": {
			"radius": 0
		},
		"ring": {
			"enabled": false,
			"colors": {
				"ring": null,
				"background": null
			},
			"effects": 0,
			"subject": {
				"scale": 1,
				"texture": null
			}
		},
		"turnMarker": {
			"mode": 1,
			"animation": null,
			"src": null,
			"disposition": false
		},
		"movementAction": null,
		"randomImg": false,
		"appendNumber": false,
		"prependAdjective": false
	},
	"effects": [],
	"system": {
		"attributes": {
			"hp": {
				"value": 215,
				"temp": 0,
				"max": 215,
				"details": "Void Healing"
			},
			"ac": {
				"value": 32,
				"details": ""
			},
			"allSaves": {
				"value": "+1 Status to All Saves vs. Divine"
			},
			"speed": {
				"value": 25,
				"otherSpeeds": [],
				"details": ""
			},
			"immunities": [
				{
					"type": "bleed"
				},
				{
					"type": "death-effects",
					"exceptions": []
				},
				{
					"type": "disease",
					"exceptions": []
				},
				{
					"type": "fire",
					"exceptions": []
				},
				{
					"type": "paralyzed",
					"exceptions": []
				},
				{
					"type": "poison",
					"exceptions": []
				},
				{
					"type": "unconscious",
					"exceptions": []
				}
			],
			"resistances": [
				{
					"type": "physical",
					"value": 15,
					"exceptions": [
						"magical"
					],
					"doubleVs": []
				}
			]
		},
		"initiative": {
			"statistic": "perception"
		},
		"details": {
			"languages": {
				"value": [
					"common",
					"necril"
				],
				"details": "Telepathy 120 feet"
			},
			"level": {
				"value": 12
			},
			"blurb": "",
			"publicNotes": "",
			"privateNotes": "",
			"publication": {
				"title": "Birreria dei Mostri",
				"authors": "Sól",
				"license": "ORC",
				"remaster": true
			},
			"license": {
				"orc": true
			}
		},
		"resources": {},
		"_migration": {
			"version": 0.955,
			"previous": {
				"schema": null,
				"foundry": "13.351",
				"system": "7.11.3"
			}
		},
		"abilities": {
			"str": {
				"mod": 7
			},
			"dex": {
				"mod": 5
			},
			"con": {
				"mod": 4
			},
			"int": {
				"mod": 4
			},
			"wis": {
				"mod": 4
			},
			"cha": {
				"mod": 7
			}
		},
		"perception": {
			"details": "",
			"mod": 22,
			"senses": [],
			"vision": true
		},
		"saves": {
			"fortitude": {
				"value": 19,
				"saveDetail": ""
			},
			"reflex": {
				"value": 22,
				"saveDetail": ""
			},
			"will": {
				"value": 25,
				"saveDetail": ""
			}
		},
		"skills": {},
		"traits": {
			"value": [
				"undead",
				"unholy"
			],
			"rarity": "uncommon",
			"size": {
				"value": "lg"
			}
		}
	},
	"img": "systems/pf2e/icons/default-icons/npc.svg",
	"items": [
		{
			"name": "Arcane Innate Spells",
			"type": "spellcastingEntry",
			"system": {
				"description": {
					"gm": "",
					"value": ""
				},
				"rules": [],
				"slug": null,
				"_migration": {
					"version": 0.955,
					"lastMigration": null,
					"previous": {
						"schema": null,
						"foundry": "13.351",
						"system": "7.11.3"
					}
				},
				"traits": {
					"otherTags": []
				},
				"publication": {
					"title": "",
					"authors": "",
					"license": "OGL",
					"remaster": false
				},
				"ability": {
					"value": "cha"
				},
				"spelldc": {
					"value": 21,
					"dc": 29
				},
				"tradition": {
					"value": "arcane"
				},
				"prepared": {
					"value": "innate"
				},
				"showSlotlessLevels": {
					"value": false
				},
				"proficiency": {
					"value": 1
				},
				"slots": {
					"slot0": {
						"prepared": [],
						"value": 0,
						"max": 0
					},
					"slot1": {
						"prepared": [],
						"value": 0,
						"max": 0
					},
					"slot2": {
						"prepared": [],
						"value": 0,
						"max": 0
					},
					"slot3": {
						"prepared": [],
						"value": 0,
						"max": 0
					},
					"slot4": {
						"prepared": [],
						"value": 0,
						"max": 0
					},
					"slot5": {
						"prepared": [],
						"value": 0,
						"max": 0
					},
					"slot6": {
						"prepared": [],
						"value": 0,
						"max": 0
					},
					"slot7": {
						"prepared": [],
						"value": 0,
						"max": 0
					},
					"slot8": {
						"prepared": [],
						"value": 0,
						"max": 0
					},
					"slot9": {
						"prepared": [],
						"value": 0,
						"max": 0
					},
					"slot10": {
						"prepared": [],
						"value": 0,
						"max": 0
					},
					"slot11": {
						"prepared": [],
						"value": 0,
						"max": 0
					}
				},
				"autoHeightenLevel": {
					"value": null
				},
				"showUnpreparedSpells": {
					"value": true
				}
			},
			"_id": "fjVWHiWAC4Q2KWRu",
			"img": "systems/pf2e/icons/default-icons/spellcastingEntry.svg",
			"effects": [],
			"folder": null,
			"sort": 0,
			"flags": {},
			"_stats": {
				"compendiumSource": null,
				"duplicateSource": null,
				"exportSource": null,
				"coreVersion": "13.351",
				"systemId": "pf2e",
				"systemVersion": "7.12.2",
				"lastModifiedBy": null
			},
			"ownership": {
				"default": 0
			},
			"_key": "!actors.items!XQdeYMt4P4zj16fM.fjVWHiWAC4Q2KWRu"
		},
		{
			"name": "Slam",
			"type": "melee",
			"system": {
				"damageRolls": {
					"strikeDamageID": {
						"damage": "3d10+14",
						"damageType": "bludgeoning",
						"category": null
					}
				},
				"bonus": {
					"value": 26
				},
				"description": {
					"value": "",
					"gm": ""
				},
				"publication": {
					"title": "",
					"authors": "",
					"license": "OGL",
					"remaster": false
				},
				"rules": [],
				"slug": null,
				"traits": {
					"otherTags": [],
					"value": [
						"reach-10",
						"unarmed"
					],
					"config": {}
				},
				"_migration": {
					"version": 0.955,
					"previous": {
						"schema": null,
						"foundry": "13.351",
						"system": "7.11.3"
					}
				},
				"action": "strike",
				"area": null,
				"attackEffects": {
					"value": []
				},
				"range": null,
				"subjectToMAP": true
			},
			"_id": "zqyRfyGR5QQ2nnCN",
			"img": "systems/pf2e/icons/default-icons/melee.svg",
			"effects": [],
			"folder": null,
			"sort": 0,
			"flags": {},
			"_stats": {
				"compendiumSource": null,
				"duplicateSource": null,
				"exportSource": null,
				"coreVersion": "13.351",
				"systemId": "pf2e",
				"systemVersion": "7.12.2",
				"lastModifiedBy": null
			},
			"ownership": {
				"default": 0
			},
			"_key": "!actors.items!XQdeYMt4P4zj16fM.zqyRfyGR5QQ2nnCN"
		},
		{
			"img": "https://assets.forge-vtt.com/bazaar/systems/pf2e/assets/icons/actions/Passive.webp",
			"name": "+1 Status to All Saves vs. Divine",
			"system": {
				"actionType": {
					"value": "passive"
				},
				"actions": {
					"value": null
				},
				"category": "defensive",
				"description": {
					"value": "",
					"gm": ""
				},
				"publication": {
					"license": "ORC",
					"remaster": true,
					"title": "Pathfinder Monster Core",
					"authors": ""
				},
				"rules": [
					{
						"key": "FlatModifier",
						"predicate": [
							"item:divine"
						],
						"selector": [
							"saving-throw"
						],
						"type": "status",
						"value": 1
					}
				],
				"traits": {
					"value": [],
					"otherTags": []
				},
				"slug": "1-status-to-all-saves-vs-magic",
				"_migration": {
					"version": 0.955,
					"previous": {
						"schema": 0.955,
						"foundry": "13.351",
						"system": "7.11.3"
					}
				},
				"deathNote": false
			},
			"type": "action",
			"_stats": {
				"compendiumSource": "Compendium.pf2e.bestiary-ability-glossary-srd.Item.kquBnQ0kObZztnBc",
				"duplicateSource": null,
				"exportSource": null,
				"coreVersion": "13.351",
				"systemId": "pf2e",
				"systemVersion": "7.12.2",
				"lastModifiedBy": null
			},
			"effects": [],
			"folder": null,
			"sort": 100000,
			"flags": {},
			"_id": "gZ9wR5rTcBVS2Cim",
			"ownership": {
				"default": 0
			},
			"_key": "!actors.items!XQdeYMt4P4zj16fM.gZ9wR5rTcBVS2Cim"
		},
		{
			"img": "https://assets.forge-vtt.com/bazaar/systems/pf2e/assets/icons/actions/Passive.webp",
			"name": "Void Healing",
			"system": {
				"actionType": {
					"value": "passive"
				},
				"actions": {
					"value": null
				},
				"category": "defensive",
				"description": {
					"value": "<p>@Localize[PF2E.NPC.Abilities.Glossary.NegativeHealing]</p>",
					"gm": ""
				},
				"publication": {
					"license": "ORC",
					"remaster": true,
					"title": "Pathfinder Monster Core",
					"authors": ""
				},
				"rules": [
					{
						"key": "ActiveEffectLike",
						"mode": "override",
						"path": "system.attributes.hp.negativeHealing",
						"value": true
					}
				],
				"traits": {
					"value": [],
					"otherTags": []
				},
				"slug": "void-healing",
				"_migration": {
					"version": 0.955,
					"previous": {
						"schema": 0.955,
						"foundry": "13.351",
						"system": "7.11.3"
					}
				}
			},
			"type": "action",
			"_stats": {
				"compendiumSource": "Compendium.pf2e.bestiary-ability-glossary-srd.Item.TTCw5NusiSSkJU1x",
				"duplicateSource": null,
				"exportSource": null,
				"coreVersion": "13.351",
				"systemId": "pf2e",
				"systemVersion": "7.12.2",
				"lastModifiedBy": null
			},
			"effects": [],
			"folder": null,
			"sort": 700000,
			"flags": {},
			"_id": "Q8clgthmsEHfvQ7i",
			"ownership": {
				"default": 0
			},
			"_key": "!actors.items!XQdeYMt4P4zj16fM.Q8clgthmsEHfvQ7i"
		},
		{
			"img": "https://assets.forge-vtt.com/bazaar/systems/pf2e/assets/icons/actions/Passive.webp",
			"name": "Telepathy (120 feet)",
			"system": {
				"actionType": {
					"value": "passive"
				},
				"actions": {
					"value": null
				},
				"category": "interaction",
				"description": {
					"value": "<p>@Localize[PF2E.NPC.Abilities.Glossary.Telepathy]</p>",
					"gm": ""
				},
				"publication": {
					"license": "ORC",
					"remaster": true,
					"title": "Pathfinder Monster Core",
					"authors": ""
				},
				"rules": [],
				"traits": {
					"value": [
						"aura",
						"magical",
						"mental"
					],
					"otherTags": []
				},
				"slug": "telepathy",
				"_migration": {
					"version": 0.955,
					"previous": {
						"schema": 0.955,
						"foundry": "13.351",
						"system": "7.11.3"
					}
				},
				"deathNote": false
			},
			"type": "action",
			"_stats": {
				"compendiumSource": "Compendium.pf2e.bestiary-ability-glossary-srd.Item.kdhbPaBMK1d1fpbA",
				"duplicateSource": null,
				"exportSource": null,
				"coreVersion": "13.351",
				"systemId": "pf2e",
				"systemVersion": "7.12.2",
				"lastModifiedBy": null
			},
			"effects": [],
			"folder": null,
			"sort": 650000,
			"flags": {},
			"_id": "X3fSAuBJ1vafKBVw",
			"ownership": {
				"default": 0
			},
			"_key": "!actors.items!XQdeYMt4P4zj16fM.X3fSAuBJ1vafKBVw"
		},
		{
			"img": "https://assets.forge-vtt.com/bazaar/systems/pf2e/assets/icons/actions/Passive.webp",
			"name": "Darkvision",
			"system": {
				"actionType": {
					"value": "passive"
				},
				"actions": {
					"value": null
				},
				"category": "interaction",
				"description": {
					"value": "<p>@Localize[PF2E.NPC.Abilities.Glossary.Darkvision]</p>",
					"gm": ""
				},
				"publication": {
					"license": "ORC",
					"remaster": true,
					"title": "Pathfinder Monster Core",
					"authors": ""
				},
				"rules": [],
				"traits": {
					"value": [],
					"otherTags": []
				},
				"slug": "darkvision",
				"_migration": {
					"version": 0.955,
					"previous": {
						"schema": 0.955,
						"foundry": "13.351",
						"system": "7.11.3"
					}
				}
			},
			"type": "action",
			"_stats": {
				"compendiumSource": "Compendium.pf2e.bestiary-ability-glossary-srd.Item.qCCLZhnp2HhP3Ex6",
				"duplicateSource": null,
				"exportSource": null,
				"coreVersion": "13.351",
				"systemId": "pf2e",
				"systemVersion": "7.12.2",
				"lastModifiedBy": null
			},
			"effects": [],
			"folder": null,
			"sort": 500000,
			"flags": {},
			"_id": "cACPUxGFJ5ty7OFr",
			"ownership": {
				"default": 0
			},
			"_key": "!actors.items!XQdeYMt4P4zj16fM.cACPUxGFJ5ty7OFr"
		},
		{
			"type": "action",
			"name": "Poisonous Aura",
			"system": {
				"actionType": {
					"value": "passive"
				},
				"description": {
					"value": "<p>@Check[fortitude|dc:29] 10 feet.</p><hr /><p>Every creature that starts their turn inside the aura must attempt at a fortitude save. Creatures who fails or critically fails are @UUID[Compendium.pf2e.conditionitems.Item.fesd1n5eVhpCSS18]{Sickened 1} (@UUID[Compendium.pf2e.conditionitems.Item.fesd1n5eVhpCSS18]{Sickened 2} with a critical fail).</p><p></p>",
					"gm": ""
				},
				"publication": {
					"title": "",
					"authors": "",
					"license": "OGL",
					"remaster": false
				},
				"rules": [
					{
						"key": "Aura",
						"radius": 10,
						"traits": [
							"divine",
							"poison"
						]
					}
				],
				"slug": null,
				"traits": {
					"otherTags": [],
					"value": [
						"aura",
						"divine",
						"poison"
					]
				},
				"_migration": {
					"version": 0.955,
					"previous": {
						"schema": 0.955,
						"foundry": "13.351",
						"system": "7.11.3"
					}
				},
				"actions": {
					"value": null
				},
				"category": "defensive",
				"deathNote": false
			},
			"effects": [],
			"_id": "PCSdNYscvu5tS2bg",
			"img": "systems/pf2e/icons/actions/Passive.webp",
			"folder": null,
			"sort": 600000,
			"flags": {},
			"_stats": {
				"compendiumSource": null,
				"duplicateSource": null,
				"exportSource": null,
				"coreVersion": "13.351",
				"systemId": "pf2e",
				"systemVersion": "7.12.2",
				"lastModifiedBy": null
			},
			"ownership": {
				"default": 0
			},
			"_key": "!actors.items!XQdeYMt4P4zj16fM.PCSdNYscvu5tS2bg"
		},
		{
			"type": "melee",
			"name": "Claws",
			"effects": [],
			"system": {
				"_migration": {
					"version": 0.955,
					"previous": {
						"schema": 0.955,
						"foundry": "13.351",
						"system": "7.11.3"
					}
				},
				"description": {
					"value": "",
					"gm": ""
				},
				"publication": {
					"title": "",
					"authors": "",
					"license": "OGL",
					"remaster": false
				},
				"rules": [],
				"slug": null,
				"traits": {
					"otherTags": [],
					"value": [
						"agile",
						"reach-10",
						"unarmed"
					],
					"config": {}
				},
				"action": "strike",
				"area": null,
				"damageRolls": {
					"xePXfalU50Jt7byK": {
						"damage": "3d8+12",
						"damageType": "slashing",
						"category": null
					}
				},
				"bonus": {
					"value": 26
				},
				"attackEffects": {
					"value": []
				},
				"range": null,
				"subjectToMAP": true
			},
			"_id": "hkCc1AmEs7jxDdrn",
			"img": "systems/pf2e/icons/default-icons/melee.svg",
			"folder": null,
			"sort": 0,
			"flags": {},
			"_stats": {
				"compendiumSource": null,
				"duplicateSource": null,
				"exportSource": null,
				"coreVersion": "13.351",
				"systemId": "pf2e",
				"systemVersion": "7.12.2",
				"lastModifiedBy": null
			},
			"ownership": {
				"default": 0
			},
			"_key": "!actors.items!XQdeYMt4P4zj16fM.hkCc1AmEs7jxDdrn"
		},
		{
			"folder": "zDlxATrLAlbYA2Mv",
			"img": "https://assets.forge-vtt.com/bazaar/systems/pf2e/assets/icons/spells/wall-of-force.webp",
			"name": "Wall of Force",
			"system": {
				"description": {
					"gm": "",
					"value": "<p>You form an @UUID[Compendium.pf2e.conditionitems.Item.zJxUflt9np0q4yML]{Invisible} wall of pure magical force up to 50 feet long and up to 20 feet high. The wall has no discernible thickness. You must create the wall in an unbroken open space so its edges don't pass through any creatures or objects, or the spell is lost. The wall has AC 10, Hardness 30, and 60 Hit Points, and it's immune to critical hits and precision damage. The wall blocks physical effects from passing through it, and because it's made of force, it blocks incorporeal and ethereal creatures as well. Teleportation effects can pass through the barrier, as can visual effects (since the wall is invisible). Wall of force is immune to counteracting effects of its level or lower, but the wall is automatically destroyed by a @UUID[Compendium.pf2e.spells-srd.Item.r7ihOgKv19eJQnik]{Disintegrate} spell of any rank.</p><hr /><p><strong>Heightened (+2)</strong> The Hit Points of the wall increase by 20.</p>"
				},
				"rules": [],
				"slug": "wall-of-force",
				"_migration": {
					"version": 0.955,
					"lastMigration": null,
					"previous": {
						"schema": 0.955,
						"foundry": "13.351",
						"system": "7.11.3"
					}
				},
				"traits": {
					"otherTags": [],
					"value": [
						"concentrate",
						"force",
						"manipulate"
					],
					"rarity": "common",
					"traditions": [
						"arcane",
						"occult"
					]
				},
				"publication": {
					"title": "Pathfinder Player Core",
					"authors": "",
					"license": "ORC",
					"remaster": true
				},
				"level": {
					"value": 6
				},
				"requirements": "",
				"target": {
					"value": ""
				},
				"range": {
					"value": "30 feet"
				},
				"area": null,
				"time": {
					"value": "3"
				},
				"duration": {
					"value": "1 minute",
					"sustained": false
				},
				"damage": {},
				"defense": null,
				"cost": {
					"value": ""
				},
				"location": {
					"value": "fjVWHiWAC4Q2KWRu",
					"heightenedLevel": 6
				},
				"counteraction": false
			},
			"type": "spell",
			"_stats": {
				"compendiumSource": "Compendium.pf2e.spells-srd.Item.7Iela4GgVeO3LfAo",
				"duplicateSource": null,
				"exportSource": null,
				"coreVersion": "13.351",
				"systemId": "pf2e",
				"systemVersion": "7.12.2",
				"lastModifiedBy": null
			},
			"effects": [],
			"sort": 0,
			"flags": {},
			"_id": "HsHFmQBqcm2S5Ea0",
			"ownership": {
				"default": 0
			},
			"_key": "!actors.items!XQdeYMt4P4zj16fM.HsHFmQBqcm2S5Ea0"
		},
		{
			"folder": "iDjm2cXyRAe4VZ35",
			"img": "https://assets.forge-vtt.com/bazaar/core/icons/creatures/slimes/slime-movement-splash-green.webp",
			"name": "Toxic Cloud",
			"system": {
				"description": {
					"gm": "",
					"value": "<p>You conjure a poisonous fog. This functions as @UUID[Compendium.pf2e.spells-srd.Item.9XHmC2JgTUIQ1CCm]{Mist}, except the area moves 10 feet away from you each round. You deal 6d8 poison damage to each breathing creature that starts its turn in the spell's area. You can Dismiss the spell.</p>\n<hr />\n<p><strong>Heightened (+1)</strong> The damage increases by 1d8.</p>"
				},
				"rules": [],
				"slug": "toxic-cloud",
				"_migration": {
					"version": 0.955,
					"lastMigration": null,
					"previous": {
						"schema": 0.955,
						"foundry": "13.351",
						"system": "7.11.3"
					}
				},
				"traits": {
					"otherTags": [],
					"value": [
						"concentrate",
						"death",
						"manipulate",
						"poison"
					],
					"rarity": "common",
					"traditions": [
						"arcane",
						"primal"
					]
				},
				"publication": {
					"title": "Pathfinder Player Core",
					"authors": "",
					"license": "ORC",
					"remaster": true
				},
				"level": {
					"value": 5
				},
				"requirements": "",
				"target": {
					"value": ""
				},
				"range": {
					"value": "120 feet"
				},
				"area": {
					"type": "burst",
					"value": 20
				},
				"time": {
					"value": "3"
				},
				"duration": {
					"value": "1 minute",
					"sustained": false
				},
				"damage": {
					"0": {
						"applyMod": false,
						"category": null,
						"formula": "6d8",
						"kinds": [
							"damage"
						],
						"materials": [],
						"type": "poison"
					}
				},
				"defense": {
					"save": {
						"basic": true,
						"statistic": "fortitude"
					}
				},
				"cost": {
					"value": ""
				},
				"location": {
					"value": "fjVWHiWAC4Q2KWRu",
					"heightenedLevel": 5
				},
				"counteraction": false,
				"heightening": {
					"area": 0,
					"damage": {
						"0": "1d8"
					},
					"interval": 1,
					"type": "interval"
				}
			},
			"type": "spell",
			"_stats": {
				"compendiumSource": "Compendium.pf2e.spells-srd.Item.MlpbeZ61Euhl0d60",
				"duplicateSource": null,
				"exportSource": null,
				"coreVersion": "13.351",
				"systemId": "pf2e",
				"systemVersion": "7.12.2",
				"lastModifiedBy": null
			},
			"effects": [],
			"sort": 0,
			"flags": {},
			"_id": "Xy6khFaF7jMzNlX7",
			"ownership": {
				"default": 0
			},
			"_key": "!actors.items!XQdeYMt4P4zj16fM.Xy6khFaF7jMzNlX7"
		},
		{
			"folder": "T8AzYUgNIAgTJ9Iz",
			"img": "https://assets.forge-vtt.com/bazaar/systems/pf2e/assets/icons/spells/noxious-vapors.webp",
			"name": "Noxious Vapors (At Will)",
			"system": {
				"description": {
					"gm": "",
					"value": "<p>You emit a cloud of toxic smoke that temporarily obscures you from sight. Each creature except you in the area when you Cast the Spell takes 1d6 poison damage (basic Fortitude save). A creature that critically fails the saving throw also becomes @UUID[Compendium.pf2e.conditionitems.Item.fesd1n5eVhpCSS18]{Sickened 1}. All creatures in the area become @UUID[Compendium.pf2e.conditionitems.Item.DmAIPqOBomZ7H95W]{Concealed}, and all creatures outside the smoke become concealed to creatures within it. This smoke can be dispersed by a strong wind.</p><hr /><p><strong>Heightened (+1)</strong> The damage increases by 1d6</p>"
				},
				"rules": [],
				"slug": "noxious-vapors",
				"_migration": {
					"version": 0.955,
					"lastMigration": null,
					"previous": {
						"schema": 0.955,
						"foundry": "13.351",
						"system": "7.11.3"
					}
				},
				"traits": {
					"otherTags": [],
					"value": [
						"concentrate",
						"manipulate",
						"poison"
					],
					"rarity": "common",
					"traditions": [
						"arcane",
						"primal"
					]
				},
				"publication": {
					"title": "Pathfinder Player Core 2",
					"authors": "",
					"license": "ORC",
					"remaster": true
				},
				"level": {
					"value": 1
				},
				"requirements": "",
				"target": {
					"value": ""
				},
				"range": {
					"value": ""
				},
				"area": {
					"type": "emanation",
					"value": 10
				},
				"time": {
					"value": "2"
				},
				"duration": {
					"value": "1 round",
					"sustained": false
				},
				"damage": {
					"0": {
						"applyMod": false,
						"category": null,
						"formula": "1d6",
						"kinds": [
							"damage"
						],
						"materials": [],
						"type": "poison"
					}
				},
				"defense": {
					"save": {
						"basic": true,
						"statistic": "fortitude"
					}
				},
				"cost": {
					"value": ""
				},
				"location": {
					"value": "fjVWHiWAC4Q2KWRu",
					"heightenedLevel": 1
				},
				"counteraction": false,
				"heightening": {
					"area": 0,
					"damage": {
						"0": "1d6"
					},
					"interval": 1,
					"type": "interval"
				}
			},
			"type": "spell",
			"_stats": {
				"compendiumSource": "Compendium.pf2e.spells-srd.Item.1meVElIu1CEVYWkv",
				"duplicateSource": null,
				"exportSource": null,
				"coreVersion": "13.351",
				"systemId": "pf2e",
				"systemVersion": "7.12.2",
				"lastModifiedBy": null
			},
			"effects": [],
			"sort": 0,
			"flags": {
				"region-attacher": {
					"attachRegionToTemplate": false
				}
			},
			"_id": "0yoVLKixhBVFO6yM",
			"ownership": {
				"default": 0
			},
			"_key": "!actors.items!XQdeYMt4P4zj16fM.0yoVLKixhBVFO6yM"
		},
		{
			"folder": "D7UVaOiB40wTR6kv",
			"img": "https://assets.forge-vtt.com/bazaar/systems/pf2e/assets/icons/spells/puff-of-poison.webp",
			"name": "Puff of Poison",
			"system": {
				"description": {
					"gm": "",
					"value": "<p>You exhale a shimmering cloud of toxic breath at an enemy's face. The target takes 1d4 poison damage and @Damage[(ceil(@item.level/2))d4[persistent,poison]], depending on its Fortitude save.</p><hr /><p><strong>Critical Success</strong> The creature is unaffected.</p>\n<p><strong>Success</strong> The target takes half initial damage and no persistent damage.</p>\n<p><strong>Failure</strong> The target takes full initial and persistent damage.</p>\n<p><strong>Critical Failure</strong> The target takes double initial and persistent damage.</p><hr /><p><strong>Heightened (+2)</strong> The initial poison damage increases by 1d4, and the persistent poison damage increases by 1d4.</p>"
				},
				"rules": [],
				"slug": "puff-of-poison",
				"_migration": {
					"version": 0.955,
					"lastMigration": null,
					"previous": {
						"schema": 0.955,
						"foundry": "13.351",
						"system": "7.11.3"
					}
				},
				"traits": {
					"otherTags": [],
					"value": [
						"cantrip",
						"concentrate",
						"manipulate",
						"poison"
					],
					"rarity": "common",
					"traditions": [
						"arcane",
						"primal"
					]
				},
				"publication": {
					"title": "Pathfinder Player Core 2",
					"authors": "",
					"license": "ORC",
					"remaster": true
				},
				"level": {
					"value": 1
				},
				"requirements": "",
				"target": {
					"value": "1 creature"
				},
				"range": {
					"value": "10 feet"
				},
				"area": null,
				"time": {
					"value": "2"
				},
				"duration": {
					"value": "",
					"sustained": false
				},
				"damage": {
					"0": {
						"applyMod": false,
						"category": null,
						"formula": "1d4",
						"kinds": [
							"damage"
						],
						"materials": [],
						"type": "poison"
					}
				},
				"defense": {
					"save": {
						"basic": false,
						"statistic": "fortitude"
					}
				},
				"cost": {
					"value": ""
				},
				"location": {
					"value": "fjVWHiWAC4Q2KWRu"
				},
				"counteraction": false,
				"heightening": {
					"damage": {
						"0": "1d4"
					},
					"interval": 2,
					"type": "interval"
				}
			},
			"type": "spell",
			"_stats": {
				"compendiumSource": "Compendium.pf2e.spells-srd.Item.D7ZEhTNIDWDLC2J4",
				"duplicateSource": null,
				"exportSource": null,
				"coreVersion": "13.351",
				"systemId": "pf2e",
				"systemVersion": "7.12.2",
				"lastModifiedBy": null
			},
			"effects": [],
			"sort": 0,
			"flags": {},
			"_id": "715YoKG786KIzM7X",
			"ownership": {
				"default": 0
			},
			"_key": "!actors.items!XQdeYMt4P4zj16fM.715YoKG786KIzM7X"
		},
		{
			"img": "https://assets.forge-vtt.com/bazaar/systems/pf2e/assets/icons/actions/Passive.webp",
			"name": "At-Will Spells",
			"system": {
				"actionType": {
					"value": "passive"
				},
				"actions": {
					"value": null
				},
				"category": "interaction",
				"description": {
					"value": "<p>@Localize[PF2E.NPC.Abilities.Glossary.AtWillSpells]</p>",
					"gm": ""
				},
				"publication": {
					"license": "ORC",
					"remaster": true,
					"title": "Pathfinder Monster Core",
					"authors": ""
				},
				"rules": [],
				"traits": {
					"value": [],
					"otherTags": []
				},
				"slug": "at-will-spells",
				"_migration": {
					"version": 0.955,
					"previous": {
						"schema": 0.955,
						"foundry": "13.351",
						"system": "7.11.3"
					}
				}
			},
			"type": "action",
			"_stats": {
				"compendiumSource": "Compendium.pf2e.bestiary-ability-glossary-srd.Item.2YRDYVnC1eljaXKK",
				"duplicateSource": null,
				"exportSource": null,
				"coreVersion": "13.351",
				"systemId": "pf2e",
				"systemVersion": "7.12.2",
				"lastModifiedBy": null
			},
			"effects": [],
			"folder": null,
			"sort": 300000,
			"flags": {},
			"_id": "wfiffc9DA3jiJGkK",
			"ownership": {
				"default": 0
			},
			"_key": "!actors.items!XQdeYMt4P4zj16fM.wfiffc9DA3jiJGkK"
		},
		{
			"type": "action",
			"name": "Breath Weapon",
			"system": {
				"actionType": {
					"value": "action"
				},
				"description": {
					"value": "<p>The rot guardian exhales a cloud of poison in a @Template[cone|distance:30], dealing @Damage[13d6[poison]] damage to all creatures in the aura (@Check[fortitude|dc:29|basic] save). The rot guardian can't use its breath weapon again for [[/gmr 1d4 #Duration]]{1d4 rounds}.</p>",
					"gm": ""
				},
				"publication": {
					"title": "",
					"authors": "",
					"license": "OGL",
					"remaster": false
				},
				"rules": [],
				"slug": null,
				"traits": {
					"otherTags": [],
					"value": [
						"concentrate",
						"divine",
						"poison"
					]
				},
				"_migration": {
					"version": 0.955,
					"previous": {
						"schema": 0.955,
						"foundry": "13.351",
						"system": "7.11.3"
					}
				},
				"actions": {
					"value": 2
				},
				"category": "offensive",
				"deathNote": false
			},
			"effects": [],
			"_id": "FET09rUFO6JXWNjU",
			"img": "systems/pf2e/icons/actions/TwoActions.webp",
			"folder": null,
			"sort": 0,
			"flags": {
				"region-attacher": {
					"attachRegionToTemplate": false
				}
			},
			"_stats": {
				"compendiumSource": null,
				"duplicateSource": null,
				"exportSource": null,
				"coreVersion": "13.351",
				"systemId": "pf2e",
				"systemVersion": "7.12.2",
				"lastModifiedBy": null
			},
			"ownership": {
				"default": 0
			},
			"_key": "!actors.items!XQdeYMt4P4zj16fM.FET09rUFO6JXWNjU"
		}
	],
	"flags": {},
	"_stats": {
		"compendiumSource": "Compendium.sol-homebrewery.Creatures.Actor.To9bYvXI0IIP0WTD",
		"duplicateSource": "Actor.yw4bl1LGPky8u6sR",
		"exportSource": null,
		"coreVersion": "13.351",
		"systemId": "pf2e",
		"systemVersion": "7.12.2",
		"createdTime": 1776116945262,
		"modifiedTime": 1776116945262,
		"lastModifiedBy": "he3UaLGz9ZNQy3ON"
	},
	"ownership": {
		"default": 0,
		"he3UaLGz9ZNQy3ON": 3
	},
	"_id": "XQdeYMt4P4zj16fM",
	"sort": 0,
	"_key": "!actors!XQdeYMt4P4zj16fM"
}
